{
    "name":"Preside Extension: Pwned Passwords",
    "version":"1.0.0",
    "author":"Sacha Moufarrege",
    "directory":"application/extensions",
    "repository":{
        "type":"git",
        "URL":"https://github.com/smoufa/preside-ext-pwnedpasswords"
    },
    "projectURL":"https://github.com/smoufa/preside-ext-pwnedpasswords",
    "location":"https://github.com/smoufa/preside-ext-pwnedpasswords/archive/v1.0.0.zip",
    "slug":"preside-ext-pwnedpasswords",
    "type":"preside-extensions",
    "ignore":[
        ".git/*",
        ".gitignore",
        ".twgit_features_subject"
    ],
}